golden/golden.py
golden-0.1.0.dist-info/LICENSE
golden-0.1.0.dist-info/METADATA
golden-0.1.0.dist-info/WHEEL
golden-0.1.0.dist-info/top_level.txt
golden-0.1.0.dist-info/RECORD
