Metadata-Version: 2.1
Name: golden
Version: 0.1.0
Summary: Python library to extract data from tech companies and topics.
Home-page: https://github.com/terrosdesigns/golden/
Author: Terros
Author-email: terrosdesigns@gmail.com
License: MIT
Platform: UNKNOWN
Classifier: Programming Language :: Python :: 3
Classifier: Natural Language :: English
Classifier: Intended Audience :: Developers
